pyredsys/__init__.py
pyredsys/constants.py
pyredsys/exceptions.py
pyredsys/form.py
pyredsys/notification.py
pyredsys/payment.py
pyredsys/py.typed
pyredsys/types.py
pyredsys/utils.py
pyredsys-0.1.6.dist-info/licenses/LICENSE
pyredsys-0.1.6.dist-info/METADATA
pyredsys-0.1.6.dist-info/WHEEL
pyredsys-0.1.6.dist-info/top_level.txt
pyredsys-0.1.6.dist-info/RECORD
