Metadata-Version: 2.4
Name: pyredsys
Version: 0.1.6
Summary: Typed RedSys integration in python
Author-email: Pradish Bijukchhe <pradish@sandbox.com.np>
License: Copyright (c) 2025 Pradish Bijukchhe
Project-URL: Homepage, https://github.com/sandbox-pokhara/pyredsys
Project-URL: Issues, https://github.com/sandbox-pokhara/pyredsys/issues
Classifier: Programming Language :: Python :: 3
Requires-Python: >=3.11
License-File: LICENSE
Requires-Dist: cryptography>=3.3.2
Requires-Dist: pydantic>=0.1
Provides-Extra: pre-commit
Requires-Dist: pre-commit; extra == "pre-commit"
Dynamic: license-file
